[{"Berechnung":{"I":{"mathjs":"Unit","value":0.024,"unit":"mA","fixPrefix":true},"G":{"mathjs":"Unit","value":0.0004,"unit":"mS","fixPrefix":true}},"Parameter":{"U":"60V"},"Eigenschaften":{"Wert":"2.5Mohm"},"Kennzeichnung":{"Art":"R","Zählnummer":1}},{"Berechnung":{"I":{"mathjs":"Unit","value":0.75,"unit":"mA","fixPrefix":true},"G":{"mathjs":"Unit","value":0.0125,"unit":"mS","fixPrefix":true}},"Parameter":{"U":"60V"},"Eigenschaften":{"Wert":"80kohm"},"Kennzeichnung":{"Art":"R","Zählnummer":2}},{"Berechnung":{"I":{"mathjs":"Unit","value":120,"unit":"mA","fixPrefix":true},"G":{"mathjs":"Unit","value":2,"unit":"mS","fixPrefix":true}},"Parameter":{"U":"60V"},"Eigenschaften":{"Wert":"500ohm"},"Kennzeichnung":{"Art":"R","Zählnummer":3}},{"Berechnung":{"I":{"mathjs":"Unit","value":800,"unit":"mA","fixPrefix":true},"G":{"mathjs":"Unit","value":13.333333333333334,"unit":"mS","fixPrefix":true}},"Parameter":{"U":"60V"},"Eigenschaften":{"Wert":"75ohm"},"Kennzeichnung":{"Art":"R","Zählnummer":4}}]