{"Kennzeichnung":{"=":{"Anlage":{"1":"","2":"","3":"","4":"","5":"","Trennzeichen":"-"}},"+":{"Ort":{"Aufstellungsort":{"1":"","2":"","3":"","4":"","5":""},"Trennzeichen":"-","Einbauort":{"6":"","7":"","8":"","9":""}}},"Art":"G","Zählnummer":"1","Funktion":"",":":[{"1":""},{"2":""}]},"visBetriebsmittel":{},"visWiderstaende":{},"nr":"g0","al":20,"width":64,"height":20,"Parameter":{"G":"3E-2S","I":"600mA","x":50,"y":50,"U12":"20 V"},"vis":{"fill":"none","style":"stroke:#ffff; stroke-width: 1.0","width":64,"height":20,"path":"M 50 50 m 0 10 l -20 0 m 84 0 l 20 0","name":"G1","value":"3E-2S","pins":[["50 - 20","10"],["154","10"]],"pointer-events":"all"}}